django_ltree_utils/__init__.py
django_ltree_utils/apps.py
django_ltree_utils/forms.py
django_ltree_utils/managers.py
django_ltree_utils/models.py
django_ltree_utils/paths.py
django_ltree_utils/position.py
django_ltree_utils/utils.py
django_ltree_utils/version.py
django_ltree_utils/views.py
django_ltree_utils/static/css/django_ltree_utils.css
django_ltree_utils/static/img/.gitignore
django_ltree_utils/static/js/django_ltree_utils.js
django_ltree_utils/templates/django_ltree_utils/base.html
django_ltree_utils/test_utils/__init__.py
django_ltree_utils/test_utils/test_app/__init__.py
django_ltree_utils/test_utils/test_app/admin.py
django_ltree_utils/test_utils/test_app/apps.py
django_ltree_utils/test_utils/test_app/models.py
django_ltree_utils/test_utils/test_app/migrations/0001_initial.py
django_ltree_utils/test_utils/test_app/migrations/0002_auto_20210401_2006.py
django_ltree_utils/test_utils/test_app/migrations/__init__.py
django_ltree_utils-0.1.7.dist-info/AUTHORS.rst
django_ltree_utils-0.1.7.dist-info/LICENSE
django_ltree_utils-0.1.7.dist-info/METADATA
django_ltree_utils-0.1.7.dist-info/WHEEL
django_ltree_utils-0.1.7.dist-info/top_level.txt
django_ltree_utils-0.1.7.dist-info/RECORD
